setup.py
download/__init__.py
download/consts.py
download/download.py
download/download_org.py
download/verse_key_converters.py
quran_downloader.egg-info/PKG-INFO
quran_downloader.egg-info/SOURCES.txt
quran_downloader.egg-info/dependency_links.txt
quran_downloader.egg-info/top_level.txt