Metadata-Version: 2.1
Name: quran-downloader
Version: 0.0.1
Summary: download quran verses
Author: Malik
Author-email: myemail46926213@gmail.com
Keywords: python,quran,audio,reciter,verses
Classifier: Development Status :: 1 - Planning
Classifier: Intended Audience :: Developers
Classifier: Programming Language :: Python :: 3
Classifier: Operating System :: Unix
Classifier: Operating System :: MacOS :: MacOS X
Classifier: Operating System :: Microsoft :: Windows
